botstrap/__init__.py
botstrap/__main__.py
botstrap/colors.py
botstrap/flow.py
botstrap/options.py
botstrap/strings.py
botstrap/cli/__init__.py
botstrap/cli/init.py
botstrap/cli/menu.py
botstrap/cli/scan.py
botstrap/cli/utils.py
botstrap/internal/__init__.py
botstrap/internal/argstrap.py
botstrap/internal/clisession.py
botstrap/internal/metadata.py
botstrap/internal/secrets.py
botstrap/internal/tokens.py
botstrap-0.2.9.dist-info/LICENSE
botstrap-0.2.9.dist-info/METADATA
botstrap-0.2.9.dist-info/WHEEL
botstrap-0.2.9.dist-info/entry_points.txt
botstrap-0.2.9.dist-info/top_level.txt
botstrap-0.2.9.dist-info/RECORD
