Metadata-Version: 2.1
Name: botstrap
Version: 0.2.9
Summary: An easy-to-use utility toolbelt for Discord bots written in Python.
Home-page: https://github.com/nuztalgia/botstrap
Author: Nuztalgia
Author-email: nuztalgia@gmail.com
License: Apache-2.0
Project-URL: Documentation, https://botstrap.readthedocs.io
Project-URL: Issue Tracker, https://github.com/nuztalgia/botstrap/issues
Project-URL: Source Code, https://github.com/nuztalgia/botstrap/tree/main/botstrap
Keywords: bot,cli,discord,encryption,security,token,utilities
Classifier: Development Status :: 4 - Beta
Classifier: Environment :: Console
Classifier: Intended Audience :: Developers
Classifier: License :: OSI Approved :: Apache Software License
Classifier: Natural Language :: English
Classifier: Operating System :: OS Independent
Classifier: Programming Language :: Python :: 3 :: Only
Classifier: Programming Language :: Python :: 3.10
Classifier: Programming Language :: Python :: 3.11
Classifier: Topic :: Communications :: Chat
Classifier: Topic :: Security :: Cryptography
Classifier: Topic :: Software Development :: Libraries :: Python Modules
Classifier: Topic :: Utilities
Classifier: Typing :: Typed
Requires-Python: >=3.10
License-File: LICENSE
Requires-Dist: colorama (>=0.4.6)
Requires-Dist: cryptography (>=39.0.0)
Provides-Extra: tests
Requires-Dist: pytest (>=7.2.1) ; extra == 'tests'
Requires-Dist: pytest-cov (>=4.0.0) ; extra == 'tests'
Requires-Dist: pytest-repeat (>=0.9.1) ; extra == 'tests'
